th_ua/__init__.py
th_ua/th_random_ua.py
th_ua-1.0.5.dist-info/METADATA
th_ua-1.0.5.dist-info/WHEEL
th_ua-1.0.5.dist-info/top_level.txt
th_ua-1.0.5.dist-info/RECORD
