Metadata-Version: 2.1
Name: th-ua
Version: 1.0.5
Summary: 听海内部爬虫核心类库
Home-page: UNKNOWN
Author: wzr
Author-email: 510540795@qq.com
License: MIT Licence
Platform: any
